pylbm/__init__.py
pylbm/boundary.py
pylbm/container.py
pylbm/context.py
pylbm/domain.py
pylbm/geometry.py
pylbm/hdf5.py
pylbm/jinja_env.py
pylbm/monitoring.py
pylbm/mpi_topology.py
pylbm/options.py
pylbm/scheme.py
pylbm/simulation.py
pylbm/stencil.py
pylbm/storage.py
pylbm/symbolic.py
pylbm/utils.py
pylbm/validator.py
pylbm/algorithm/__init__.py
pylbm/algorithm/base.py
pylbm/algorithm/ode.py
pylbm/algorithm/pull.py
pylbm/algorithm/transform.py
pylbm/analysis/__init__.py
pylbm/analysis/equivalent_equation.py
pylbm/analysis/stability.py
pylbm/elements/__init__.py
pylbm/elements/base.py
pylbm/elements/circle.py
pylbm/elements/cylinder.py
pylbm/elements/ellipse.py
pylbm/elements/ellipsoid.py
pylbm/elements/parallelogram.py
pylbm/elements/sphere.py
pylbm/elements/stl_element.py
pylbm/elements/triangle.py
pylbm/elements/utils.py
pylbm/generator/__init__.py
pylbm/generator/ast.py
pylbm/generator/autowrap.py
pylbm/generator/codegen.py
pylbm/generator/generator.py
pylbm/generator/printing/__init__.py
pylbm/generator/printing/cython.py
pylbm/generator/printing/loopy.py
pylbm/generator/printing/pycode.py
pylbm/templates/circle.tpl
pylbm/templates/cylinder.tpl
pylbm/templates/domain.tpl
pylbm/templates/ellipse.tpl
pylbm/templates/ellipsoid.tpl
pylbm/templates/equivalent_equation.tpl
pylbm/templates/geometry.tpl
pylbm/templates/scheme.tpl
pylbm/templates/simulation.tpl
pylbm/templates/square.tpl
pylbm/templates/stencil.tpl
pylbm/templates/stl.tpl
pylbm/templates/wrap.tpl
pylbm/viewer/__init__.py
pylbm/viewer/base.py
pylbm/viewer/matplotlib_viewer.py
pylbm/viewer/vispyViewer.py_tofix
pylbm-0.9.0.dist-info/METADATA
pylbm-0.9.0.dist-info/WHEEL
pylbm-0.9.0.dist-info/licenses/LICENSE
pylbm-0.9.0.dist-info/RECORD
