Metadata-Version: 2.1
Name: pylbm
Version: 0.9.0
Summary: A flexible Python package for lattice Boltzmann method
Project-URL: Source, https://github.com/pylbm/pylbm
Project-URL: Documentation, https://pylbm.readthedocs.io
Author-email: Benjamin Graille <benjamin.graille@universite-paris-saclay.fr>, Loic Gouarin <loic.gouarin@polytechnique.edu>
License-Expression: BSD-3-Clause
License-File: LICENSE
Keywords: Boltzmann,Lattice,Methods
Classifier: Intended Audience :: Developers
Classifier: Intended Audience :: Science/Research
Classifier: License :: OSI Approved :: BSD License
Classifier: Operating System :: MacOS
Classifier: Operating System :: Microsoft :: Windows
Classifier: Operating System :: POSIX
Classifier: Operating System :: Unix
Classifier: Programming Language :: Cython
Classifier: Programming Language :: Python
Classifier: Programming Language :: Python :: 3
Classifier: Programming Language :: Python :: 3 :: Only
Classifier: Programming Language :: Python :: 3.6
Classifier: Programming Language :: Python :: 3.7
Classifier: Programming Language :: Python :: 3.8
Classifier: Programming Language :: Python :: 3.9
Classifier: Topic :: Scientific/Engineering
Classifier: Topic :: Scientific/Engineering :: Mathematics
Classifier: Topic :: Scientific/Engineering :: Physics
Classifier: Topic :: Software Development
Classifier: Topic :: Software Development :: Code Generators
Requires-Python: >=3.6
Requires-Dist: cerberus
Requires-Dist: colorama
Requires-Dist: colorlog
Requires-Dist: cython
Requires-Dist: h5py
Requires-Dist: jinja2
Requires-Dist: matplotlib
Requires-Dist: mpi4py
Requires-Dist: numpy
Requires-Dist: numpy-stl
Requires-Dist: sympy>=1.3
Provides-Extra: gpu
Requires-Dist: loo-py==2017.2; extra == 'gpu'
Requires-Dist: pyopencl; extra == 'gpu'
